rebot/__init__.py
rebot/rebot.py
rebot/regular.py
rebot/t.py
rebot/utu.py
rebot-1.4.dist-info/LICENSE
rebot-1.4.dist-info/METADATA
rebot-1.4.dist-info/WHEEL
rebot-1.4.dist-info/top_level.txt
rebot-1.4.dist-info/RECORD
