Metadata-Version: 2.1
Name: rebot
Version: 1.4
Summary: this llib make telebot more easy.
Home-page: 
Author: ReBack
Author-email: 
Project-URL: Bug Tracker, https://github.com/pypa/sampleproject/issues
Keywords: telebot
Classifier: Development Status :: 1 - Planning
Classifier: Intended Audience :: Developers
Classifier: Programming Language :: Python :: 3
Classifier: Operating System :: Unix
Classifier: Operating System :: MacOS :: MacOS X
Classifier: Operating System :: Microsoft :: Windows
License-File: LICENSE
Requires-Dist: requests
Requires-Dist: telebot
